compiler/__init__.py
compiler/api/__init__.py
compiler/api/compiler.py
compiler/errors/__init__.py
compiler/errors/compiler.py
compiler/errors/sort.py
telefusion/__init__.py
telefusion/client.py
telefusion/dispatcher.py
telefusion/emoji.py
telefusion/file_id.py
telefusion/filters.py
telefusion/mime_types.py
telefusion/py.typed
telefusion/sync.py
telefusion/utils.py
telefusion/connection/__init__.py
telefusion/connection/connection.py
telefusion/connection/transport/__init__.py
telefusion/connection/transport/tcp/__init__.py
telefusion/connection/transport/tcp/tcp.py
telefusion/connection/transport/tcp/tcp_abridged.py
telefusion/connection/transport/tcp/tcp_abridged_o.py
telefusion/connection/transport/tcp/tcp_full.py
telefusion/connection/transport/tcp/tcp_intermediate.py
telefusion/connection/transport/tcp/tcp_intermediate_o.py
telefusion/crypto/__init__.py
telefusion/crypto/aes.py
telefusion/crypto/mtproto.py
telefusion/crypto/prime.py
telefusion/crypto/rsa.py
telefusion/enums/__init__.py
telefusion/enums/auto_name.py
telefusion/enums/chat_action.py
telefusion/enums/chat_event_action.py
telefusion/enums/chat_member_status.py
telefusion/enums/chat_members_filter.py
telefusion/enums/chat_type.py
telefusion/enums/listerner_types.py
telefusion/enums/message_entity_type.py
telefusion/enums/message_media_type.py
telefusion/enums/message_service_type.py
telefusion/enums/messages_filter.py
telefusion/enums/next_code_type.py
telefusion/enums/parse_mode.py
telefusion/enums/poll_type.py
telefusion/enums/profile_color.py
telefusion/enums/reply_color.py
telefusion/enums/sent_code_type.py
telefusion/enums/stories_privacy_rules.py
telefusion/enums/story_privacy.py
telefusion/enums/user_status.py
telefusion/errors/__init__.py
telefusion/errors/rpc_error.py
telefusion/errors/pyromod/__init__.py
telefusion/errors/pyromod/listener_stopped.py
telefusion/errors/pyromod/listener_timeout.py
telefusion/handlers/__init__.py
telefusion/handlers/callback_query_handler.py
telefusion-1.169.0.dist-info/METADATA
telefusion-1.169.0.dist-info/NOTICE
telefusion-1.169.0.dist-info/WHEEL
telefusion-1.169.0.dist-info/top_level.txt
telefusion-1.169.0.dist-info/RECORD
